<?xml version='1.0' encoding='UTF-8' standalone='yes' ?>
<hierarchy index="0" class="hierarchy" rotation="0" width="1080" height="2072">
  <android.widget.FrameLayout index="0" package="com.amazon.kindle" class="android.widget.FrameLayout" text="" checkable="false" checked="false" clickable="false" enabled="true" focusable="false" focused="false" long-clickable="false" password="false" scrollable="false" selected="false" bounds="[0,0][1080,2340]" displayed="true">
    <android.widget.LinearLayout index="0" package="com.amazon.kindle" class="android.widget.LinearLayout" text="" checkable="false" checked="false" clickable="false" enabled="true" focusable="false" focused="false" long-clickable="false" password="false" scrollable="false" selected="false" bounds="[0,0][1080,2208]" displayed="true">
      <android.widget.FrameLayout index="0" package="com.amazon.kindle" class="android.widget.FrameLayout" text="" checkable="false" checked="false" clickable="false" enabled="true" focusable="false" focused="false" long-clickable="false" password="false" scrollable="false" selected="false" bounds="[0,145][1080,2208]" displayed="true">
        <android.widget.LinearLayout index="0" package="com.amazon.kindle" class="android.widget.LinearLayout" text="" resource-id="com.amazon.kindle:id/action_bar_root" checkable="false" checked="false" clickable="false" enabled="true" focusable="false" focused="false" long-clickable="false" password="false" scrollable="false" selected="false" bounds="[0,145][1080,2208]" displayed="true">
          <android.widget.FrameLayout index="0" package="com.amazon.kindle" class="android.widget.FrameLayout" text="" resource-id="android:id/content" checkable="false" checked="false" clickable="false" enabled="true" focusable="false" focused="false" long-clickable="false" password="false" scrollable="false" selected="false" bounds="[0,145][1080,2208]" displayed="true">
            <android.widget.FrameLayout index="0" package="com.amazon.kindle" class="android.widget.FrameLayout" text="" resource-id="com.amazon.kindle:id/library_root_view" checkable="false" checked="false" clickable="false" enabled="true" focusable="false" focused="false" long-clickable="false" password="false" scrollable="false" selected="false" bounds="[0,145][1080,2208]" displayed="true">
              <android.widget.FrameLayout index="0" package="com.amazon.kindle" class="android.widget.FrameLayout" text="" resource-id="com.amazon.kindle:id/main_view_bottom_sheet_container" checkable="false" checked="false" clickable="false" enabled="true" focusable="false" focused="false" long-clickable="false" password="false" scrollable="false" selected="false" bounds="[0,145][1080,2208]" displayed="true" />
              <android.widget.LinearLayout index="1" package="com.amazon.kindle" class="android.widget.LinearLayout" text="" checkable="false" checked="false" clickable="false" enabled="true" focusable="false" focused="false" long-clickable="false" password="false" scrollable="false" selected="false" bounds="[0,145][1080,2208]" displayed="true">
                <android.widget.LinearLayout index="0" package="com.amazon.kindle" class="android.widget.LinearLayout" text="" checkable="false" checked="false" clickable="false" enabled="true" focusable="false" focused="false" long-clickable="false" password="false" scrollable="false" selected="false" bounds="[0,145][1080,313]" displayed="true">
                  <android.view.ViewGroup index="0" package="com.amazon.kindle" class="android.view.ViewGroup" text="" resource-id="com.amazon.kindle:id/top_bar" checkable="false" checked="false" clickable="false" enabled="true" focusable="false" focused="false" long-clickable="false" password="false" scrollable="false" selected="false" bounds="[0,145][1080,313]" displayed="true">
                    <android.widget.LinearLayout index="0" package="com.amazon.kindle" class="android.widget.LinearLayout" text="" resource-id="com.amazon.kindle:id/search_box" checkable="false" checked="false" clickable="true" enabled="true" focusable="true" focused="false" long-clickable="false" password="false" scrollable="false" selected="false" bounds="[44,172][926,283]" displayed="true">
                      <android.widget.ImageView index="0" package="com.amazon.kindle" class="android.widget.ImageView" text="" checkable="false" checked="false" clickable="false" enabled="true" focusable="false" focused="false" long-clickable="false" password="false" scrollable="false" selected="false" bounds="[66,194][132,260]" displayed="true" />
                      <android.widget.TextView index="1" package="com.amazon.kindle" class="android.widget.TextView" text="Search Kindle" resource-id="com.amazon.kindle:id/search_box_text_view" checkable="false" checked="false" clickable="false" enabled="true" focusable="false" focused="false" long-clickable="false" password="false" scrollable="false" selected="false" bounds="[165,172][407,283]" displayed="true" />
                    </android.widget.LinearLayout>
                    <androidx.appcompat.widget.LinearLayoutCompat index="1" package="com.amazon.kindle" class="androidx.appcompat.widget.LinearLayoutCompat" text="" checkable="false" checked="false" clickable="false" enabled="true" focusable="false" focused="false" long-clickable="false" password="false" scrollable="false" selected="false" bounds="[931,152][1080,306]" displayed="true">
                      <android.widget.RelativeLayout index="0" package="com.amazon.kindle" class="android.widget.RelativeLayout" text="" content-desc="Notifications. Button. 3 new notifications." resource-id="com.amazon.kindle:id/landing_screen_action" checkable="false" checked="false" clickable="true" enabled="true" focusable="true" focused="false" long-clickable="false" password="false" scrollable="false" selected="false" bounds="[931,157][1080,300]" displayed="true">
                        <android.widget.ImageView index="0" package="com.amazon.kindle" class="android.widget.ImageView" text="" resource-id="com.amazon.kindle:id/landing_screen_action_image" checkable="false" checked="false" clickable="false" enabled="true" focusable="false" focused="false" long-clickable="false" password="false" scrollable="false" selected="false" bounds="[965,195][1031,261]" displayed="true" />
                        <android.widget.TextView index="1" package="com.amazon.kindle" class="android.widget.TextView" text="3" resource-id="com.amazon.kindle:id/landing_screen_action_badge" checkable="false" checked="false" clickable="false" enabled="true" focusable="false" focused="false" long-clickable="false" password="false" scrollable="false" selected="false" bounds="[1001,195][1040,228]" displayed="true" />
                      </android.widget.RelativeLayout>
                    </androidx.appcompat.widget.LinearLayoutCompat>
                  </android.view.ViewGroup>
                </android.widget.LinearLayout>
                <android.view.ViewGroup index="1" package="com.amazon.kindle" class="android.view.ViewGroup" text="" resource-id="com.amazon.kindle:id/screenlet_container" checkable="false" checked="false" clickable="false" enabled="true" focusable="false" focused="false" long-clickable="false" password="false" scrollable="false" selected="false" bounds="[0,313][1080,2040]" displayed="true">
                  <android.widget.FrameLayout index="0" package="com.amazon.kindle" class="android.widget.FrameLayout" text="" resource-id="com.amazon.kindle:id/more_screenlet_root" checkable="false" checked="false" clickable="false" enabled="true" focusable="false" focused="false" long-clickable="false" password="false" scrollable="false" selected="false" bounds="[0,313][1080,2040]" displayed="true">
                    <android.widget.ListView index="0" package="com.amazon.kindle" class="android.widget.ListView" text="" resource-id="com.amazon.kindle:id/items_screen_list" checkable="false" checked="false" clickable="false" enabled="true" focusable="true" focused="false" long-clickable="false" password="false" scrollable="false" selected="false" bounds="[0,313][1080,2040]" displayed="true">
                      <android.widget.Button index="0" package="com.amazon.kindle" class="android.widget.Button" text="" content-desc="Sync Now, Last synced on 03/12/2025, 5:17 PM" resource-id="com.amazon.kindle:id/sync_item_id" checkable="false" checked="false" clickable="false" enabled="true" focusable="false" focused="false" long-clickable="false" password="false" scrollable="false" selected="false" bounds="[0,313][1080,467]" displayed="true">
                        <android.widget.LinearLayout index="0" package="com.amazon.kindle" class="android.widget.LinearLayout" text="" checkable="false" checked="false" clickable="false" enabled="true" focusable="false" focused="false" long-clickable="false" password="false" scrollable="false" selected="false" bounds="[0,313][1080,464]" displayed="true">
                          <android.widget.ImageView index="0" package="com.amazon.kindle" class="android.widget.ImageView" text="" resource-id="com.amazon.kindle:id/sync_item_icon" checkable="false" checked="false" clickable="false" enabled="true" focusable="false" focused="false" long-clickable="false" password="false" scrollable="false" selected="false" bounds="[44,355][110,421]" displayed="true" />
                          <android.widget.LinearLayout index="1" package="com.amazon.kindle" class="android.widget.LinearLayout" text="" checkable="false" checked="false" clickable="false" enabled="true" focusable="false" focused="false" long-clickable="false" password="false" scrollable="false" selected="false" bounds="[143,340][1036,437]" displayed="true">
                            <android.widget.TextView index="0" package="com.amazon.kindle" class="android.widget.TextView" text="Sync Now" resource-id="com.amazon.kindle:id/sync_item_title" checkable="false" checked="false" clickable="false" enabled="true" focusable="false" focused="false" long-clickable="false" password="false" scrollable="false" selected="false" bounds="[143,340][1036,395]" displayed="true" />
                            <android.widget.TextView index="1" package="com.amazon.kindle" class="android.widget.TextView" text="Last synced on 03/12/2025, 5:23 PM" resource-id="com.amazon.kindle:id/sync_item_status" checkable="false" checked="false" clickable="false" enabled="true" focusable="false" focused="false" long-clickable="false" password="false" scrollable="false" selected="false" bounds="[143,398][1036,437]" displayed="true" />
                          </android.widget.LinearLayout>
                        </android.widget.LinearLayout>
                        <android.view.View index="1" package="com.amazon.kindle" class="android.view.View" text="" checkable="false" checked="false" clickable="false" enabled="true" focusable="false" focused="false" long-clickable="false" password="false" scrollable="false" selected="false" bounds="[44,464][1036,467]" displayed="true" />
                      </android.widget.Button>
                      <android.widget.Button index="1" package="com.amazon.kindle" class="android.widget.Button" text="" content-desc="Read &amp; Listen with Audible" checkable="false" checked="false" clickable="true" enabled="true" focusable="true" focused="false" long-clickable="false" password="false" scrollable="false" selected="false" bounds="[0,467][1080,621]" displayed="true">
                        <android.widget.LinearLayout index="0" package="com.amazon.kindle" class="android.widget.LinearLayout" text="" checkable="false" checked="false" clickable="false" enabled="true" focusable="false" focused="false" long-clickable="false" password="false" scrollable="false" selected="false" bounds="[0,467][1080,618]" displayed="true">
                          <android.widget.ImageView index="0" package="com.amazon.kindle" class="android.widget.ImageView" text="" resource-id="com.amazon.kindle:id/item_icon" checkable="false" checked="false" clickable="false" enabled="true" focusable="false" focused="false" long-clickable="false" password="false" scrollable="false" selected="false" bounds="[44,509][110,575]" displayed="true" />
                          <android.widget.LinearLayout index="1" package="com.amazon.kindle" class="android.widget.LinearLayout" text="" checkable="false" checked="false" clickable="false" enabled="true" focusable="false" focused="false" long-clickable="false" password="false" scrollable="false" selected="false" bounds="[143,515][687,570]" displayed="true">
                            <android.widget.TextView index="0" package="com.amazon.kindle" class="android.widget.TextView" text="Read &amp; Listen with Audible" resource-id="com.amazon.kindle:id/item_title" checkable="false" checked="false" clickable="false" enabled="true" focusable="false" focused="false" long-clickable="false" password="false" scrollable="false" selected="false" bounds="[143,515][687,570]" displayed="true" />
                          </android.widget.LinearLayout>
                        </android.widget.LinearLayout>
                        <android.view.View index="1" package="com.amazon.kindle" class="android.view.View" text="" checkable="false" checked="false" clickable="false" enabled="true" focusable="false" focused="false" long-clickable="false" password="false" scrollable="false" selected="false" bounds="[44,618][1036,621]" displayed="true" />
                      </android.widget.Button>
                      <android.widget.Button index="2" package="com.amazon.kindle" class="android.widget.Button" text="" content-desc="Reading Challenges, Previously Reading Insights" checkable="false" checked="false" clickable="true" enabled="true" focusable="true" focused="false" long-clickable="false" password="false" scrollable="false" selected="false" bounds="[0,621][1080,775]" displayed="true">
                        <android.widget.LinearLayout index="0" package="com.amazon.kindle" class="android.widget.LinearLayout" text="" checkable="false" checked="false" clickable="false" enabled="true" focusable="false" focused="false" long-clickable="false" password="false" scrollable="false" selected="false" bounds="[0,621][1080,772]" displayed="true">
                          <android.widget.ImageView index="0" package="com.amazon.kindle" class="android.widget.ImageView" text="" resource-id="com.amazon.kindle:id/item_icon" checkable="false" checked="false" clickable="false" enabled="true" focusable="false" focused="false" long-clickable="false" password="false" scrollable="false" selected="false" bounds="[44,663][110,729]" displayed="true" />
                          <android.widget.LinearLayout index="1" package="com.amazon.kindle" class="android.widget.LinearLayout" text="" checkable="false" checked="false" clickable="false" enabled="true" focusable="false" focused="false" long-clickable="false" password="false" scrollable="false" selected="false" bounds="[143,648][547,745]" displayed="true">
                            <android.widget.TextView index="0" package="com.amazon.kindle" class="android.widget.TextView" text="Reading Challenges" resource-id="com.amazon.kindle:id/item_title" checkable="false" checked="false" clickable="false" enabled="true" focusable="false" focused="false" long-clickable="false" password="false" scrollable="false" selected="false" bounds="[143,648][547,703]" displayed="true" />
                            <android.widget.TextView index="1" package="com.amazon.kindle" class="android.widget.TextView" text="Previously Reading Insights" resource-id="com.amazon.kindle:id/item_subtitle" checkable="false" checked="false" clickable="false" enabled="true" focusable="false" focused="false" long-clickable="false" password="false" scrollable="false" selected="false" bounds="[143,706][547,745]" displayed="true" />
                          </android.widget.LinearLayout>
                        </android.widget.LinearLayout>
                        <android.view.View index="1" package="com.amazon.kindle" class="android.view.View" text="" checkable="false" checked="false" clickable="false" enabled="true" focusable="false" focused="false" long-clickable="false" password="false" scrollable="false" selected="false" bounds="[44,772][1036,775]" displayed="true" />
                      </android.widget.Button>
                      <android.widget.Button index="3" package="com.amazon.kindle" class="android.widget.Button" text="" content-desc="Your Lists" checkable="false" checked="false" clickable="true" enabled="true" focusable="true" focused="false" long-clickable="false" password="false" scrollable="false" selected="false" bounds="[0,775][1080,929]" displayed="true">
                        <android.widget.LinearLayout index="0" package="com.amazon.kindle" class="android.widget.LinearLayout" text="" checkable="false" checked="false" clickable="false" enabled="true" focusable="false" focused="false" long-clickable="false" password="false" scrollable="false" selected="false" bounds="[0,775][1080,926]" displayed="true">
                          <android.widget.ImageView index="0" package="com.amazon.kindle" class="android.widget.ImageView" text="" resource-id="com.amazon.kindle:id/item_icon" checkable="false" checked="false" clickable="false" enabled="true" focusable="false" focused="false" long-clickable="false" password="false" scrollable="false" selected="false" bounds="[44,817][110,883]" displayed="true" />
                          <android.widget.LinearLayout index="1" package="com.amazon.kindle" class="android.widget.LinearLayout" text="" checkable="false" checked="false" clickable="false" enabled="true" focusable="false" focused="false" long-clickable="false" password="false" scrollable="false" selected="false" bounds="[143,823][337,878]" displayed="true">
                            <android.widget.TextView index="0" package="com.amazon.kindle" class="android.widget.TextView" text="Your Lists" resource-id="com.amazon.kindle:id/item_title" checkable="false" checked="false" clickable="false" enabled="true" focusable="false" focused="false" long-clickable="false" password="false" scrollable="false" selected="false" bounds="[143,823][337,878]" displayed="true" />
                          </android.widget.LinearLayout>
                        </android.widget.LinearLayout>
                        <android.view.View index="1" package="com.amazon.kindle" class="android.view.View" text="" checkable="false" checked="false" clickable="false" enabled="true" focusable="false" focused="false" long-clickable="false" password="false" scrollable="false" selected="false" bounds="[44,926][1036,929]" displayed="true" />
                      </android.widget.Button>
                      <android.widget.Button index="4" package="com.amazon.kindle" class="android.widget.Button" text="" content-desc="Kindle Unlimited Membership" checkable="false" checked="false" clickable="true" enabled="true" focusable="true" focused="false" long-clickable="false" password="false" scrollable="false" selected="false" bounds="[0,929][1080,1083]" displayed="true">
                        <android.widget.LinearLayout index="0" package="com.amazon.kindle" class="android.widget.LinearLayout" text="" checkable="false" checked="false" clickable="false" enabled="true" focusable="false" focused="false" long-clickable="false" password="false" scrollable="false" selected="false" bounds="[0,929][1080,1080]" displayed="true">
                          <android.widget.ImageView index="0" package="com.amazon.kindle" class="android.widget.ImageView" text="" resource-id="com.amazon.kindle:id/item_icon" checkable="false" checked="false" clickable="false" enabled="true" focusable="false" focused="false" long-clickable="false" password="false" scrollable="false" selected="false" bounds="[44,971][110,1037]" displayed="true" />
                          <android.widget.LinearLayout index="1" package="com.amazon.kindle" class="android.widget.LinearLayout" text="" checkable="false" checked="false" clickable="false" enabled="true" focusable="false" focused="false" long-clickable="false" password="false" scrollable="false" selected="false" bounds="[143,977][745,1032]" displayed="true">
                            <android.widget.TextView index="0" package="com.amazon.kindle" class="android.widget.TextView" text="Kindle Unlimited Membership" resource-id="com.amazon.kindle:id/item_title" checkable="false" checked="false" clickable="false" enabled="true" focusable="false" focused="false" long-clickable="false" password="false" scrollable="false" selected="false" bounds="[143,977][745,1032]" displayed="true" />
                          </android.widget.LinearLayout>
                        </android.widget.LinearLayout>
                        <android.view.View index="1" package="com.amazon.kindle" class="android.view.View" text="" checkable="false" checked="false" clickable="false" enabled="true" focusable="false" focused="false" long-clickable="false" password="false" scrollable="false" selected="false" bounds="[44,1080][1036,1083]" displayed="true" />
                      </android.widget.Button>
                      <android.widget.Button index="5" package="com.amazon.kindle" class="android.widget.Button" text="" content-desc="Notebooks" checkable="false" checked="false" clickable="true" enabled="true" focusable="true" focused="false" long-clickable="false" password="false" scrollable="false" selected="false" bounds="[0,1083][1080,1237]" displayed="true">
                        <android.widget.LinearLayout index="0" package="com.amazon.kindle" class="android.widget.LinearLayout" text="" checkable="false" checked="false" clickable="false" enabled="true" focusable="false" focused="false" long-clickable="false" password="false" scrollable="false" selected="false" bounds="[0,1083][1080,1234]" displayed="true">
                          <android.widget.ImageView index="0" package="com.amazon.kindle" class="android.widget.ImageView" text="" resource-id="com.amazon.kindle:id/item_icon" checkable="false" checked="false" clickable="false" enabled="true" focusable="false" focused="false" long-clickable="false" password="false" scrollable="false" selected="false" bounds="[44,1125][110,1191]" displayed="true" />
                          <android.widget.LinearLayout index="1" package="com.amazon.kindle" class="android.widget.LinearLayout" text="" checkable="false" checked="false" clickable="false" enabled="true" focusable="false" focused="false" long-clickable="false" password="false" scrollable="false" selected="false" bounds="[143,1131][362,1186]" displayed="true">
                            <android.widget.TextView index="0" package="com.amazon.kindle" class="android.widget.TextView" text="Notebooks" resource-id="com.amazon.kindle:id/item_title" checkable="false" checked="false" clickable="false" enabled="true" focusable="false" focused="false" long-clickable="false" password="false" scrollable="false" selected="false" bounds="[143,1131][362,1186]" displayed="true" />
                          </android.widget.LinearLayout>
                        </android.widget.LinearLayout>
                        <android.view.View index="1" package="com.amazon.kindle" class="android.view.View" text="" checkable="false" checked="false" clickable="false" enabled="true" focusable="false" focused="false" long-clickable="false" password="false" scrollable="false" selected="false" bounds="[44,1234][1036,1237]" displayed="true" />
                      </android.widget.Button>
                      <android.widget.Button index="6" package="com.amazon.kindle" class="android.widget.Button" text="" content-desc="Household Sharing" checkable="false" checked="false" clickable="true" enabled="true" focusable="true" focused="false" long-clickable="false" password="false" scrollable="false" selected="false" bounds="[0,1237][1080,1391]" displayed="true">
                        <android.widget.LinearLayout index="0" package="com.amazon.kindle" class="android.widget.LinearLayout" text="" checkable="false" checked="false" clickable="false" enabled="true" focusable="false" focused="false" long-clickable="false" password="false" scrollable="false" selected="false" bounds="[0,1237][1080,1388]" displayed="true">
                          <android.widget.ImageView index="0" package="com.amazon.kindle" class="android.widget.ImageView" text="" resource-id="com.amazon.kindle:id/item_icon" checkable="false" checked="false" clickable="false" enabled="true" focusable="false" focused="false" long-clickable="false" password="false" scrollable="false" selected="false" bounds="[44,1279][110,1345]" displayed="true" />
                          <android.widget.LinearLayout index="1" package="com.amazon.kindle" class="android.widget.LinearLayout" text="" checkable="false" checked="false" clickable="false" enabled="true" focusable="false" focused="false" long-clickable="false" password="false" scrollable="false" selected="false" bounds="[143,1285][525,1340]" displayed="true">
                            <android.widget.TextView index="0" package="com.amazon.kindle" class="android.widget.TextView" text="Household Sharing" resource-id="com.amazon.kindle:id/item_title" checkable="false" checked="false" clickable="false" enabled="true" focusable="false" focused="false" long-clickable="false" password="false" scrollable="false" selected="false" bounds="[143,1285][525,1340]" displayed="true" />
                          </android.widget.LinearLayout>
                        </android.widget.LinearLayout>
                        <android.view.View index="1" package="com.amazon.kindle" class="android.view.View" text="" checkable="false" checked="false" clickable="false" enabled="true" focusable="false" focused="false" long-clickable="false" password="false" scrollable="false" selected="false" bounds="[44,1388][1036,1391]" displayed="true" />
                      </android.widget.Button>
                      <android.widget.Button index="7" package="com.amazon.kindle" class="android.widget.Button" text="" content-desc="Settings" checkable="false" checked="false" clickable="true" enabled="true" focusable="true" focused="false" long-clickable="false" password="false" scrollable="false" selected="false" bounds="[0,1391][1080,1545]" displayed="true">
                        <android.widget.LinearLayout index="0" package="com.amazon.kindle" class="android.widget.LinearLayout" text="" checkable="false" checked="false" clickable="false" enabled="true" focusable="false" focused="false" long-clickable="false" password="false" scrollable="false" selected="false" bounds="[0,1391][1080,1542]" displayed="true">
                          <android.widget.ImageView index="0" package="com.amazon.kindle" class="android.widget.ImageView" text="" resource-id="com.amazon.kindle:id/item_icon" checkable="false" checked="false" clickable="false" enabled="true" focusable="false" focused="false" long-clickable="false" password="false" scrollable="false" selected="false" bounds="[44,1433][110,1499]" displayed="true" />
                          <android.widget.LinearLayout index="1" package="com.amazon.kindle" class="android.widget.LinearLayout" text="" checkable="false" checked="false" clickable="false" enabled="true" focusable="false" focused="false" long-clickable="false" password="false" scrollable="false" selected="false" bounds="[143,1439][308,1494]" displayed="true">
                            <android.widget.TextView index="0" package="com.amazon.kindle" class="android.widget.TextView" text="Settings" resource-id="com.amazon.kindle:id/item_title" checkable="false" checked="false" clickable="false" enabled="true" focusable="false" focused="false" long-clickable="false" password="false" scrollable="false" selected="false" bounds="[143,1439][308,1494]" displayed="true" />
                          </android.widget.LinearLayout>
                        </android.widget.LinearLayout>
                        <android.view.View index="1" package="com.amazon.kindle" class="android.view.View" text="" checkable="false" checked="false" clickable="false" enabled="true" focusable="false" focused="false" long-clickable="false" password="false" scrollable="false" selected="false" bounds="[44,1542][1036,1545]" displayed="true" />
                      </android.widget.Button>
                      <android.widget.Button index="8" package="com.amazon.kindle" class="android.widget.Button" text="" content-desc="Help &amp; Feedback" checkable="false" checked="false" clickable="true" enabled="true" focusable="true" focused="false" long-clickable="false" password="false" scrollable="false" selected="false" bounds="[0,1545][1080,1699]" displayed="true">
                        <android.widget.LinearLayout index="0" package="com.amazon.kindle" class="android.widget.LinearLayout" text="" checkable="false" checked="false" clickable="false" enabled="true" focusable="false" focused="false" long-clickable="false" password="false" scrollable="false" selected="false" bounds="[0,1545][1080,1696]" displayed="true">
                          <android.widget.ImageView index="0" package="com.amazon.kindle" class="android.widget.ImageView" text="" resource-id="com.amazon.kindle:id/item_icon" checkable="false" checked="false" clickable="false" enabled="true" focusable="false" focused="false" long-clickable="false" password="false" scrollable="false" selected="false" bounds="[44,1587][110,1653]" displayed="true" />
                          <android.widget.LinearLayout index="1" package="com.amazon.kindle" class="android.widget.LinearLayout" text="" checkable="false" checked="false" clickable="false" enabled="true" focusable="false" focused="false" long-clickable="false" password="false" scrollable="false" selected="false" bounds="[143,1593][483,1648]" displayed="true">
                            <android.widget.TextView index="0" package="com.amazon.kindle" class="android.widget.TextView" text="Help &amp; Feedback" resource-id="com.amazon.kindle:id/item_title" checkable="false" checked="false" clickable="false" enabled="true" focusable="false" focused="false" long-clickable="false" password="false" scrollable="false" selected="false" bounds="[143,1593][483,1648]" displayed="true" />
                          </android.widget.LinearLayout>
                        </android.widget.LinearLayout>
                        <android.view.View index="1" package="com.amazon.kindle" class="android.view.View" text="" checkable="false" checked="false" clickable="false" enabled="true" focusable="false" focused="false" long-clickable="false" password="false" scrollable="false" selected="false" bounds="[44,1696][1036,1699]" displayed="true" />
                      </android.widget.Button>
                      <android.widget.Button index="9" package="com.amazon.kindle" class="android.widget.Button" text="" content-desc="Info" checkable="false" checked="false" clickable="true" enabled="true" focusable="true" focused="false" long-clickable="false" password="false" scrollable="false" selected="false" bounds="[0,1699][1080,1853]" displayed="true">
                        <android.widget.LinearLayout index="0" package="com.amazon.kindle" class="android.widget.LinearLayout" text="" checkable="false" checked="false" clickable="false" enabled="true" focusable="false" focused="false" long-clickable="false" password="false" scrollable="false" selected="false" bounds="[0,1699][1080,1850]" displayed="true">
                          <android.widget.ImageView index="0" package="com.amazon.kindle" class="android.widget.ImageView" text="" resource-id="com.amazon.kindle:id/item_icon" checkable="false" checked="false" clickable="false" enabled="true" focusable="false" focused="false" long-clickable="false" password="false" scrollable="false" selected="false" bounds="[44,1741][110,1807]" displayed="true" />
                          <android.widget.LinearLayout index="1" package="com.amazon.kindle" class="android.widget.LinearLayout" text="" checkable="false" checked="false" clickable="false" enabled="true" focusable="false" focused="false" long-clickable="false" password="false" scrollable="false" selected="false" bounds="[143,1747][225,1802]" displayed="true">
                            <android.widget.TextView index="0" package="com.amazon.kindle" class="android.widget.TextView" text="Info" resource-id="com.amazon.kindle:id/item_title" checkable="false" checked="false" clickable="false" enabled="true" focusable="false" focused="false" long-clickable="false" password="false" scrollable="false" selected="false" bounds="[143,1747][225,1802]" displayed="true" />
                          </android.widget.LinearLayout>
                        </android.widget.LinearLayout>
                        <android.view.View index="1" package="com.amazon.kindle" class="android.view.View" text="" checkable="false" checked="false" clickable="false" enabled="true" focusable="false" focused="false" long-clickable="false" password="false" scrollable="false" selected="false" bounds="[44,1850][1036,1853]" displayed="true" />
                      </android.widget.Button>
                      <android.widget.Button index="10" package="com.amazon.kindle" class="android.widget.Button" text="" content-desc="Sign Out, Registered to sam@solreader.com" checkable="false" checked="false" clickable="true" enabled="true" focusable="true" focused="false" long-clickable="false" password="false" scrollable="false" selected="false" bounds="[0,1853][1080,2007]" displayed="true">
                        <android.widget.LinearLayout index="0" package="com.amazon.kindle" class="android.widget.LinearLayout" text="" checkable="false" checked="false" clickable="false" enabled="true" focusable="false" focused="false" long-clickable="false" password="false" scrollable="false" selected="false" bounds="[0,1853][1080,2004]" displayed="true">
                          <android.widget.ImageView index="0" package="com.amazon.kindle" class="android.widget.ImageView" text="" resource-id="com.amazon.kindle:id/item_icon" checkable="false" checked="false" clickable="false" enabled="true" focusable="false" focused="false" long-clickable="false" password="false" scrollable="false" selected="false" bounds="[44,1895][110,1961]" displayed="true" />
                          <android.widget.LinearLayout index="1" package="com.amazon.kindle" class="android.widget.LinearLayout" text="" checkable="false" checked="false" clickable="false" enabled="true" focusable="false" focused="false" long-clickable="false" password="false" scrollable="false" selected="false" bounds="[143,1880][646,1977]" displayed="true">
                            <android.widget.TextView index="0" package="com.amazon.kindle" class="android.widget.TextView" text="Sign Out" resource-id="com.amazon.kindle:id/item_title" checkable="false" checked="false" clickable="false" enabled="true" focusable="false" focused="false" long-clickable="false" password="false" scrollable="false" selected="false" bounds="[143,1880][646,1935]" displayed="true" />
                            <android.widget.TextView index="1" package="com.amazon.kindle" class="android.widget.TextView" text="Registered to sam@solreader.com" resource-id="com.amazon.kindle:id/item_subtitle" checkable="false" checked="false" clickable="false" enabled="true" focusable="false" focused="false" long-clickable="false" password="false" scrollable="false" selected="false" bounds="[143,1938][646,1977]" displayed="true" />
                          </android.widget.LinearLayout>
                        </android.widget.LinearLayout>
                        <android.view.View index="1" package="com.amazon.kindle" class="android.view.View" text="" checkable="false" checked="false" clickable="false" enabled="true" focusable="false" focused="false" long-clickable="false" password="false" scrollable="false" selected="false" bounds="[44,2004][1036,2007]" displayed="true" />
                      </android.widget.Button>
                    </android.widget.ListView>
                  </android.widget.FrameLayout>
                </android.view.ViewGroup>
                <android.view.View index="2" package="com.amazon.kindle" class="android.view.View" text="" resource-id="com.amazon.kindle:id/bottom_bar_background" checkable="false" checked="false" clickable="false" enabled="true" focusable="false" focused="false" long-clickable="false" password="false" scrollable="false" selected="false" bounds="[0,2040][1080,2208]" displayed="true" />
              </android.widget.LinearLayout>
              <android.widget.LinearLayout index="2" package="com.amazon.kindle" class="android.widget.LinearLayout" text="" resource-id="com.amazon.kindle:id/bottom_bar_inflated" checkable="false" checked="false" clickable="false" enabled="true" focusable="false" focused="false" long-clickable="false" password="false" scrollable="false" selected="false" bounds="[0,1988][1080,2208]" displayed="true">
                <android.widget.LinearLayout index="0" package="com.amazon.kindle" class="android.widget.LinearLayout" text="" resource-id="com.amazon.kindle:id/bottom_bar" checkable="false" checked="false" clickable="false" enabled="true" focusable="false" focused="false" long-clickable="false" password="false" scrollable="false" selected="false" bounds="[0,1988][1080,2208]" displayed="true">
                  <android.widget.FrameLayout index="0" package="com.amazon.kindle" class="android.widget.FrameLayout" text="" checkable="false" checked="false" clickable="true" enabled="true" focusable="true" focused="false" long-clickable="false" password="false" scrollable="false" selected="false" bounds="[0,1988][270,2208]" displayed="true">
                    <android.widget.ImageView index="0" package="com.amazon.kindle" class="android.widget.ImageView" text="" content-desc="Most recent book. Poor Charlie’s Almanack: The Essential Wit and Wisdom of Charles T. Munger, Munger, Charles T., , New, Book downloaded., " resource-id="com.amazon.kindle:id/book_in_bottom_bar" checkable="false" checked="false" clickable="false" enabled="true" focusable="false" focused="false" long-clickable="false" password="false" scrollable="false" selected="false" bounds="[65,1988][204,2186]" displayed="true" />
                  </android.widget.FrameLayout>
                  <android.widget.LinearLayout index="1" package="com.amazon.kindle" class="android.widget.LinearLayout" text="" content-desc="Home, Tab" resource-id="com.amazon.kindle:id/home_tab" checkable="false" checked="false" clickable="true" enabled="true" focusable="true" focused="false" long-clickable="false" password="false" scrollable="false" selected="false" bounds="[270,2040][540,2208]" displayed="true">
                    <android.widget.ImageView index="0" package="com.amazon.kindle" class="android.widget.ImageView" text="" resource-id="com.amazon.kindle:id/icon" checkable="false" checked="false" clickable="false" enabled="true" focusable="false" focused="false" long-clickable="false" password="false" scrollable="false" selected="false" bounds="[372,2070][438,2136]" displayed="true" />
                    <android.widget.TextView index="1" package="com.amazon.kindle" class="android.widget.TextView" text="HOME" resource-id="com.amazon.kindle:id/label" checkable="false" checked="false" clickable="false" enabled="true" focusable="false" focused="false" long-clickable="false" password="false" scrollable="false" selected="false" bounds="[364,2147][446,2180]" displayed="true" />
                  </android.widget.LinearLayout>
                  <android.widget.LinearLayout index="2" package="com.amazon.kindle" class="android.widget.LinearLayout" text="" content-desc="LIBRARY, Tab" resource-id="com.amazon.kindle:id/library_tab" checkable="false" checked="false" clickable="true" enabled="true" focusable="true" focused="false" long-clickable="false" password="false" scrollable="false" selected="false" bounds="[540,2040][810,2208]" displayed="true">
                    <android.widget.ImageView index="0" package="com.amazon.kindle" class="android.widget.ImageView" text="" resource-id="com.amazon.kindle:id/icon" checkable="false" checked="false" clickable="false" enabled="true" focusable="false" focused="false" long-clickable="false" password="false" scrollable="false" selected="false" bounds="[642,2070][708,2136]" displayed="true" />
                    <android.widget.TextView index="1" package="com.amazon.kindle" class="android.widget.TextView" text="LIBRARY" resource-id="com.amazon.kindle:id/label" checkable="false" checked="false" clickable="false" enabled="true" focusable="false" focused="false" long-clickable="false" password="false" scrollable="false" selected="false" bounds="[620,2147][729,2180]" displayed="true" />
                  </android.widget.LinearLayout>
                  <android.widget.LinearLayout index="3" package="com.amazon.kindle" class="android.widget.LinearLayout" text="" content-desc="More, Tab selected" resource-id="com.amazon.kindle:id/more_tab" checkable="false" checked="false" clickable="true" enabled="true" focusable="true" focused="false" long-clickable="false" password="false" scrollable="false" selected="false" bounds="[810,2040][1080,2208]" displayed="true">
                    <android.widget.ImageView index="0" package="com.amazon.kindle" class="android.widget.ImageView" text="" resource-id="com.amazon.kindle:id/icon" checkable="false" checked="false" clickable="false" enabled="true" focusable="false" focused="false" long-clickable="false" password="false" scrollable="false" selected="true" bounds="[912,2070][978,2136]" displayed="true" />
                    <android.widget.TextView index="1" package="com.amazon.kindle" class="android.widget.TextView" text="MORE" resource-id="com.amazon.kindle:id/label" checkable="false" checked="false" clickable="false" enabled="true" focusable="false" focused="false" long-clickable="false" password="false" scrollable="false" selected="true" bounds="[906,2147][984,2180]" displayed="true" />
                  </android.widget.LinearLayout>
                </android.widget.LinearLayout>
              </android.widget.LinearLayout>
            </android.widget.FrameLayout>
          </android.widget.FrameLayout>
        </android.widget.LinearLayout>
      </android.widget.FrameLayout>
    </android.widget.LinearLayout>
  </android.widget.FrameLayout>
</hierarchy>